pydrumscore/__init__.py
pydrumscore/__main__.py
pydrumscore/__version__.py
pydrumscore/api.py
pydrumscore/beats.py
pydrumscore/default_config.ini
pydrumscore/export.py
pydrumscore/requirements.txt
pydrumscore/msplugins/RefreshScorePlugin.qml
pydrumscore/refxml/PartXML.xml
pydrumscore/test/__init__.py
pydrumscore/test/test_base.py
pydrumscore/test/cases/__init__.py
pydrumscore/test/cases/beats/__init__.py
pydrumscore/test/cases/beats/test_beats.py
pydrumscore/test/cases/beats/data/Bd_1_and_3.mscx
pydrumscore/test/cases/beats/data/Flam_1b.mscx
pydrumscore/test/cases/beats/data/Ghost_1b.mscx
pydrumscore/test/cases/beats/data/MoneyBeat_1b.mscx
pydrumscore/test/cases/beats/data/MoneyBeat_Accents_1b.mscx
pydrumscore/test/cases/beats/data/RockBeatWOpen_1b.mscx
pydrumscore/test/cases/beats/data/RockBeat_1b.mscx
pydrumscore/test/cases/beats/data/Sextuplets.mscx
pydrumscore/test/cases/beats/data/ShuffleBeat_1b.mscx
pydrumscore/test/cases/beats/data/Silence_1b.mscx
pydrumscore/test/cases/beats/songs/__init__.py
pydrumscore/test/cases/beats/songs/bd_1_and_3.py
pydrumscore/test/cases/beats/songs/flam_1b.py
pydrumscore/test/cases/beats/songs/ghost_1b.py
pydrumscore/test/cases/beats/songs/sextuplets.py
pydrumscore/test/cases/beats/songs/song_money_beat.py
pydrumscore/test/cases/beats/songs/song_money_beat_accents.py
pydrumscore/test/cases/beats/songs/song_rock_beat.py
pydrumscore/test/cases/beats/songs/song_rock_beat_wopen.py
pydrumscore/test/cases/beats/songs/song_shuffle_beat.py
pydrumscore/test/cases/cli/__init__.py
pydrumscore/test/cases/cli/song_accented_metadata.py
pydrumscore/test/cases/cli/song_no_measures.py
pydrumscore/test/cases/cli/song_no_metadata.py
pydrumscore/test/cases/cli/song_no_metadata_or_measures.py
pydrumscore/test/cases/cli/song_silence.py
pydrumscore/test/cases/cli/test_cli.py
pydrumscore/test/cases/cli/data/Rémy's Wonderful Song.mscx
pydrumscore/test/cases/cli/data/Silence_1b.mscx
pydrumscore/test/cases/exercises/__init__.py
pydrumscore-0.0.6.dist-info/LICENSE.md
pydrumscore-0.0.6.dist-info/METADATA
pydrumscore-0.0.6.dist-info/WHEEL
pydrumscore-0.0.6.dist-info/entry_points.txt
pydrumscore-0.0.6.dist-info/top_level.txt
pydrumscore-0.0.6.dist-info/RECORD
