Metadata-Version: 2.1
Name: pydrumscore
Version: 0.0.6
Summary: A python interface for generating drum sheet music through code
Author: Rémy Lapointe
License: GNU GPL
Project-URL: Documentation, https://www.remylapointe.com/PyDrumScore
Project-URL: GitHub, https://github.com/dual-wield-ray/PyDrumScore
Classifier: Programming Language :: Python :: 3
Requires-Python: >=3.8
License-File: LICENSE.md
Requires-Dist: requests
Requires-Dist: xmldiff
Requires-Dist: from-root (<=1.0.2)
Requires-Dist: setuptools-scm
Requires-Dist: importlib-metadata ; python_version > "3.8"
